xldg/__init__.py
xldg/core.py
xldg/data.py
xldg/graphics.py
xldg-0.3.6.dist-info/licenses/LICENSE
xldg-0.3.6.dist-info/METADATA
xldg-0.3.6.dist-info/WHEEL
xldg-0.3.6.dist-info/top_level.txt
xldg-0.3.6.dist-info/RECORD
