Metadata-Version: 2.4
Name: xldg
Version: 0.3.6
Summary: XLDataGraph is a library for crosslinking data analysis and visualization.
Author: a-helix
Project-URL: Homepage, https://github.com/a-helix/XLDataGraph
Project-URL: Bug Tracker, https://github.com/a-helix/XLDataGraph/issues
Classifier: Programming Language :: Python :: 3
Classifier: Operating System :: OS Independent
Requires-Python: >=3.7
License-File: LICENSE
Requires-Dist: requests>=2.32.3
Requires-Dist: pyCirclize>=1.6.0
Requires-Dist: matplotlib_venn>=1.1.2
Requires-Dist: networkx>=3.4.2
Dynamic: license-file
